{
  "lastUpdated": "2026-05-31T14:54:07.510Z",
  "jackpots": {
    "magnum": {},
    "damacai": {},
    "toto": {}
  },
  "draws": [
    {
      "date": "2026-05-31",
      "dateDisplay": "2026年5月31日 (日)",
      "operators": {
        "magnum": {
          "name": "万能 Magnum 4D",
          "drawNo": "",
          "first": "0000",
          "second": "0000",
          "third": "0000",
          "special": [],
          "consolation": []
        },
        "damacai": null,
        "toto": null
      }
    },
    {
      "date": "2026-05-30",
      "dateDisplay": "2026年5月30日 (六)",
      "operators": {
        "magnum": {
          "name": "万能 Magnum 4D",
          "drawNo": "",
          "first": "0000",
          "second": "0000",
          "third": "0000",
          "special": [],
          "consolation": []
        },
        "damacai": null,
        "toto": null
      }
    },
    {
      "date": "2026-05-27",
      "dateDisplay": "2026年5月27日 (三)",
      "operators": {
        "magnum": {
          "name": "万能 Magnum 4D",
          "drawNo": "",
          "first": "0000",
          "second": "0000",
          "third": "0000",
          "special": [],
          "consolation": []
        },
        "damacai": null,
        "toto": null
      }
    },
    {
      "date": "2026-05-24",
      "dateDisplay": "2026年5月24日 (日)",
      "operators": {
        "magnum": {
          "name": "万能 Magnum 4D",
          "drawNo": "",
          "first": "0000",
          "second": "0000",
          "third": "0000",
          "special": [],
          "consolation": []
        },
        "damacai": null,
        "toto": null
      }
    },
    {
      "date": "2026-05-23",
      "dateDisplay": "2026年5月23日 (六)",
      "operators": {
        "magnum": {
          "name": "万能 Magnum 4D",
          "drawNo": "",
          "first": "0000",
          "second": "0000",
          "third": "0000",
          "special": [],
          "consolation": []
        },
        "damacai": null,
        "toto": null
      }
    },
    {
      "date": "2026-05-20",
      "dateDisplay": "2026年5月20日 (三)",
      "operators": {
        "magnum": {
          "name": "万能 Magnum 4D",
          "drawNo": "",
          "first": "0000",
          "second": "0000",
          "third": "0000",
          "special": [],
          "consolation": []
        },
        "damacai": null,
        "toto": null
      }
    },
    {
      "date": "2026-05-17",
      "dateDisplay": "2026年5月17日 (日)",
      "operators": {
        "magnum": {
          "name": "万能 Magnum 4D",
          "drawNo": "",
          "first": "0000",
          "second": "0000",
          "third": "0000",
          "special": [],
          "consolation": []
        },
        "damacai": null,
        "toto": null
      }
    },
    {
      "date": "2026-05-16",
      "dateDisplay": "2026年5月16日 (六)",
      "operators": {
        "magnum": {
          "name": "万能 Magnum 4D",
          "drawNo": "",
          "first": "0000",
          "second": "0000",
          "third": "0000",
          "special": [],
          "consolation": []
        },
        "damacai": null,
        "toto": null
      }
    },
    {
      "date": "2026-05-13",
      "dateDisplay": "2026年5月13日 (三)",
      "operators": {
        "magnum": {
          "name": "万能 Magnum 4D",
          "drawNo": "",
          "first": "0000",
          "second": "0000",
          "third": "0000",
          "special": [],
          "consolation": []
        },
        "damacai": null,
        "toto": null
      }
    },
    {
      "date": "2026-05-10",
      "dateDisplay": "2026年5月10日 (日)",
      "operators": {
        "magnum": {
          "name": "万能 Magnum 4D",
          "drawNo": "",
          "first": "0000",
          "second": "0000",
          "third": "0000",
          "special": [],
          "consolation": []
        },
        "damacai": null,
        "toto": null
      }
    }
  ]
}